WuaiPojieLuntanjinghuaJi2015/README.md
WuaiPojieLuntanjinghuaJi2015/__init__.py
WuaiPojieLuntanjinghuaJi2015/__main__.py
WuaiPojieLuntanjinghuaJi2015/file.epub
WuaiPojieLuntanjinghuaJi2015/index.html
WuaiPojieLuntanjinghuaJi2015/css/__init__.py
WuaiPojieLuntanjinghuaJi2015/css/annotations.css
WuaiPojieLuntanjinghuaJi2015/css/main.css
WuaiPojieLuntanjinghuaJi2015/css/normalize.css
WuaiPojieLuntanjinghuaJi2015/css/popup.css
WuaiPojieLuntanjinghuaJi2015/font/__init__.py
WuaiPojieLuntanjinghuaJi2015/font/fontello.eot
WuaiPojieLuntanjinghuaJi2015/font/fontello.svg
WuaiPojieLuntanjinghuaJi2015/font/fontello.ttf
WuaiPojieLuntanjinghuaJi2015/font/fontello.woff
WuaiPojieLuntanjinghuaJi2015/img/__init__.py
WuaiPojieLuntanjinghuaJi2015/img/annotator-glyph-sprite.png
WuaiPojieLuntanjinghuaJi2015/img/annotator-icon-sprite.png
WuaiPojieLuntanjinghuaJi2015/img/apple-touch-icon.png
WuaiPojieLuntanjinghuaJi2015/img/cancelfullscreen.png
WuaiPojieLuntanjinghuaJi2015/img/close.png
WuaiPojieLuntanjinghuaJi2015/img/fullscreen.png
WuaiPojieLuntanjinghuaJi2015/img/loader.gif
WuaiPojieLuntanjinghuaJi2015/img/menu-icon.png
WuaiPojieLuntanjinghuaJi2015/img/save.png
WuaiPojieLuntanjinghuaJi2015/img/saved.png
WuaiPojieLuntanjinghuaJi2015/img/settings-s.png
WuaiPojieLuntanjinghuaJi2015/img/settings.png
WuaiPojieLuntanjinghuaJi2015/img/star.png
WuaiPojieLuntanjinghuaJi2015/js/__init__.py
WuaiPojieLuntanjinghuaJi2015/js/epub.js
WuaiPojieLuntanjinghuaJi2015/js/epub.min.js
WuaiPojieLuntanjinghuaJi2015/js/epub.min.map
WuaiPojieLuntanjinghuaJi2015/js/hooks.min.js
WuaiPojieLuntanjinghuaJi2015/js/hooks.min.map
WuaiPojieLuntanjinghuaJi2015/js/reader.js
WuaiPojieLuntanjinghuaJi2015/js/reader.js.map
WuaiPojieLuntanjinghuaJi2015/js/reader.min.js
WuaiPojieLuntanjinghuaJi2015/js/reader.min.map
WuaiPojieLuntanjinghuaJi2015/js/hooks/__init__.py
WuaiPojieLuntanjinghuaJi2015/js/hooks/extensions/__init__.py
WuaiPojieLuntanjinghuaJi2015/js/hooks/extensions/highlight.js
wuai_pojie_luntanjinghua_ji_2015-2024.3.6.0.dist-info/METADATA
wuai_pojie_luntanjinghua_ji_2015-2024.3.6.0.dist-info/WHEEL
wuai_pojie_luntanjinghua_ji_2015-2024.3.6.0.dist-info/entry_points.txt
wuai_pojie_luntanjinghua_ji_2015-2024.3.6.0.dist-info/top_level.txt
wuai_pojie_luntanjinghua_ji_2015-2024.3.6.0.dist-info/RECORD
